{"users":[{"name":"Lucas Fernandes 4wwasaseew11","email":"fernandes20lucas@hotmail.com"},{"id":"d000dec2-8656-4769-8fff-145a3de19f8e","name":"Lucas Fernandes 4wwasaseew11","email":"fernandes20lucas@hotmail.com"},{"id":"8e31004c-2adb-4ca2-9cbf-1d0c7fe76c74","name":"Lucas Fernandes 4wwasaseew11","email":"fernandes20lucas@hotmail.com"},{"id":"0d429d00-69bf-4aae-bc1b-89ad0b4a54ad","name":"Lucas Fernandes 4wwasaseew11","email":"fernandes20lucas@hotmail.com"},{"id":"bc6c1f7e-1546-4c88-b2c5-ffb0351f1f5b","name":"LucasTeste","email":"LucasTeste@hotmail.com"}],"tasks":[{"id":"98260123-4e28-48e8-bb6d-206fc3b6a145","title":"Americado","description":"Americado@hotmailassas.com","updated_at":1690484238765},{"id":"c4450e93-e452-472b-99c5-c279d40b7195","title":"Estudar","description":"conteudo de node","created_at":1690484276722,"completed_at":"","updated_at":""},{"id":"3bff3a49-43fb-4a15-a16a-430563b745c5","title":"Estudar 2","description":"conteudo de node","created_at":1690484640690,"completed_at":"","updated_at":""},{"id":"30c7ddc0-d1f2-479a-97a7-327144729ee9","title":"Estudar 3","description":"conteudo de node","created_at":1690484730902,"completed_at":"","updated_at":""}]}